hellebore_otcstreaming/__init__.py
hellebore_otcstreaming/exceptions.py
hellebore_otcstreaming/isda.py
hellebore_otcstreaming-0.1.1.dist-info/WHEEL
hellebore_otcstreaming-0.1.1.dist-info/METADATA
hellebore_otcstreaming-0.1.1.dist-info/RECORD
