Metadata-Version: 2.1
Name: hellebore-otcstreaming
Version: 0.1.1
Summary: API Wrapper for OTCStreaming.
Author: Benjamin Denise
Author-email: bdenise@helleboretech.com
Requires-Python: >=3.9,<4.0
Classifier: Programming Language :: Python :: 3
Classifier: Programming Language :: Python :: 3.10
Classifier: Programming Language :: Python :: 3.9
Provides-Extra: test
Requires-Dist: requests (>=2.27.1,<3.0.0)
